<annotation>
	<bam_src>https://mir-s3-cdn-cf.behance.net/project_modules/disp/5d9c6520057369.562ebdce60002.JPG</bam_src>
	<filename>137718391</filename>
	<size>
		<width>600</width>
		<height>450</height>
		<depth>3</depth>
	</size>
	<object>
		<name>cat</name>
		<pose>Unspecified</pose>
		<truncated>0</truncated>
		<difficult>0</difficult>
		<bndbox>
			<xmin>308</xmin>
			<ymin>44</ymin>
			<xmax>599</xmax>
			<ymax>439</ymax>
		</bndbox>
	</object>
	<object>
		<name>cat</name>
		<pose>Unspecified</pose>
		<truncated>0</truncated>
		<difficult>0</difficult>
		<bndbox>
			<xmin>21</xmin>
			<ymin>34</ymin>
			<xmax>297</xmax>
			<ymax>444</ymax>
		</bndbox>
	</object>
</annotation>
