<annotation>
	<bam_src>https://mir-s3-cdn-cf.behance.net/project_modules/disp/cbbfab24388741.563335b1e307e.jpg</bam_src>
	<filename>161159941</filename>
	<size>
		<width>555</width>
		<height>740</height>
		<depth>3</depth>
	</size>
	<object>
		<name>person</name>
		<pose>Unspecified</pose>
		<truncated>0</truncated>
		<difficult>0</difficult>
		<bndbox>
			<xmin>70</xmin>
			<ymin>431</ymin>
			<xmax>265</xmax>
			<ymax>705</ymax>
		</bndbox>
	</object>
	<object>
		<name>person</name>
		<pose>Unspecified</pose>
		<truncated>0</truncated>
		<difficult>0</difficult>
		<bndbox>
			<xmin>275</xmin>
			<ymin>443</ymin>
			<xmax>447</xmax>
			<ymax>650</ymax>
		</bndbox>
	</object>
	<object>
		<name>person</name>
		<pose>Unspecified</pose>
		<truncated>0</truncated>
		<difficult>0</difficult>
		<bndbox>
			<xmin>279</xmin>
			<ymin>16</ymin>
			<xmax>511</xmax>
			<ymax>282</ymax>
		</bndbox>
	</object>
	<object>
		<name>person</name>
		<pose>Unspecified</pose>
		<truncated>0</truncated>
		<difficult>0</difficult>
		<bndbox>
			<xmin>107</xmin>
			<ymin>34</ymin>
			<xmax>263</xmax>
			<ymax>246</ymax>
		</bndbox>
	</object>
</annotation>
