<annotation>
	<bam_src>https://mir-s3-cdn-cf.behance.net/project_modules/disp/90ec7033533985.56af01c67a192.jpg</bam_src>
	<filename>212104227</filename>
	<size>
		<width>600</width>
		<height>383</height>
		<depth>3</depth>
	</size>
	<object>
		<name>bird</name>
		<pose>Unspecified</pose>
		<truncated>0</truncated>
		<difficult>0</difficult>
		<bndbox>
			<xmin>339</xmin>
			<ymin>9</ymin>
			<xmax>439</xmax>
			<ymax>116</ymax>
		</bndbox>
	</object>
	<object>
		<name>bird</name>
		<pose>Unspecified</pose>
		<truncated>0</truncated>
		<difficult>0</difficult>
		<bndbox>
			<xmin>371</xmin>
			<ymin>125</ymin>
			<xmax>481</xmax>
			<ymax>309</ymax>
		</bndbox>
	</object>
	<object>
		<name>bird</name>
		<pose>Unspecified</pose>
		<truncated>0</truncated>
		<difficult>0</difficult>
		<bndbox>
			<xmin>202</xmin>
			<ymin>104</ymin>
			<xmax>319</xmax>
			<ymax>312</ymax>
		</bndbox>
	</object>
	<object>
		<name>bird</name>
		<pose>Unspecified</pose>
		<truncated>0</truncated>
		<difficult>0</difficult>
		<bndbox>
			<xmin>458</xmin>
			<ymin>141</ymin>
			<xmax>524</xmax>
			<ymax>330</ymax>
		</bndbox>
	</object>
</annotation>
