<annotation>
	<cmplaces_id>000000000193</cmplaces_id>
	<filename>16170368.jpg</filename>
	<size>
		<width>240</width>
		<height>160</height>
		<depth>3</depth>
	</size>
	<object>
		<name>diningtable</name>
		<pose>Unspecified</pose>
		<truncated>0</truncated>
		<difficult>0</difficult>
		<bndbox>
			<xmin>88</xmin>
			<ymin>93</ymin>
			<xmax>179</xmax>
			<ymax>150</ymax>
		</bndbox>
	</object>
	<object>
		<name>chair</name>
		<pose>Unspecified</pose>
		<truncated>0</truncated>
		<difficult>0</difficult>
		<bndbox>
			<xmin>43</xmin>
			<ymin>72</ymin>
			<xmax>94</xmax>
			<ymax>140</ymax>
		</bndbox>
	</object>
	<object>
		<name>sofa</name>
		<pose>Unspecified</pose>
		<truncated>0</truncated>
		<difficult>0</difficult>
		<bndbox>
			<xmin>161</xmin>
			<ymin>57</ymin>
			<xmax>238</xmax>
			<ymax>151</ymax>
		</bndbox>
	</object>
</annotation>
