<annotation>
	<cmplaces_id>000000002409</cmplaces_id>
	<filename>738773822.jpg</filename>
	<size>
		<width>318</width>
		<height>442</height>
		<depth>3</depth>
	</size>
	<object>
		<name>pottedplant</name>
		<pose>Unspecified</pose>
		<truncated>0</truncated>
		<difficult>0</difficult>
		<bndbox>
			<xmin>26</xmin>
			<ymin>143</ymin>
			<xmax>75</xmax>
			<ymax>230</ymax>
		</bndbox>
	</object>
	<object>
		<name>person</name>
		<pose>Unspecified</pose>
		<truncated>0</truncated>
		<difficult>0</difficult>
		<bndbox>
			<xmin>28</xmin>
			<ymin>72</ymin>
			<xmax>163</xmax>
			<ymax>415</ymax>
		</bndbox>
	</object>
	<object>
		<name>person</name>
		<pose>Unspecified</pose>
		<truncated>0</truncated>
		<difficult>0</difficult>
		<bndbox>
			<xmin>199</xmin>
			<ymin>93</ymin>
			<xmax>303</xmax>
			<ymax>420</ymax>
		</bndbox>
	</object>
</annotation>
